odoo/addons/l10n_be_mis_reports/README.rst
odoo/addons/l10n_be_mis_reports/__init__.py
odoo/addons/l10n_be_mis_reports/__manifest__.py
odoo/addons/l10n_be_mis_reports/data/mis_report_bs_deprecated.xml
odoo/addons/l10n_be_mis_reports/data/mis_report_bs_m01-f.xml
odoo/addons/l10n_be_mis_reports/data/mis_report_bs_m02-f.xml
odoo/addons/l10n_be_mis_reports/data/mis_report_bs_m04-f.xml
odoo/addons/l10n_be_mis_reports/data/mis_report_bs_m05-f.xml
odoo/addons/l10n_be_mis_reports/data/mis_report_bs_m07-f.xml
odoo/addons/l10n_be_mis_reports/data/mis_report_bs_m08-f.xml
odoo/addons/l10n_be_mis_reports/data/mis_report_bs_m81-f.xml
odoo/addons/l10n_be_mis_reports/data/mis_report_bs_m82-f.xml
odoo/addons/l10n_be_mis_reports/data/mis_report_bs_m87-f.xml
odoo/addons/l10n_be_mis_reports/data/mis_report_pl_deprecated.xml
odoo/addons/l10n_be_mis_reports/data/mis_report_pl_m01-f.xml
odoo/addons/l10n_be_mis_reports/data/mis_report_pl_m02-f.xml
odoo/addons/l10n_be_mis_reports/data/mis_report_pl_m04-f.xml
odoo/addons/l10n_be_mis_reports/data/mis_report_pl_m05-f.xml
odoo/addons/l10n_be_mis_reports/data/mis_report_pl_m07-f.xml
odoo/addons/l10n_be_mis_reports/data/mis_report_pl_m08-f.xml
odoo/addons/l10n_be_mis_reports/data/mis_report_pl_m81-f.xml
odoo/addons/l10n_be_mis_reports/data/mis_report_pl_m82-f.xml
odoo/addons/l10n_be_mis_reports/data/mis_report_pl_m87-f.xml
odoo/addons/l10n_be_mis_reports/data/mis_report_styles.xml
odoo/addons/l10n_be_mis_reports/data/mis_report_vat.xml
odoo/addons/l10n_be_mis_reports/i18n/de.po
odoo/addons/l10n_be_mis_reports/i18n/es.po
odoo/addons/l10n_be_mis_reports/i18n/fr.po
odoo/addons/l10n_be_mis_reports/i18n/l10n_be_mis_reports.pot
odoo/addons/l10n_be_mis_reports/i18n/nl.po
odoo/addons/l10n_be_mis_reports/readme/CONFIGURE.md
odoo/addons/l10n_be_mis_reports/readme/CONTRIBUTORS.md
odoo/addons/l10n_be_mis_reports/readme/DESCRIPTION.md
odoo/addons/l10n_be_mis_reports/readme/INSTALL.md
odoo/addons/l10n_be_mis_reports/readme/USAGE.md
odoo_addon_l10n_be_mis_reports-18.0.1.0.0.2.dist-info/METADATA
odoo_addon_l10n_be_mis_reports-18.0.1.0.0.2.dist-info/WHEEL
odoo_addon_l10n_be_mis_reports-18.0.1.0.0.2.dist-info/top_level.txt
odoo_addon_l10n_be_mis_reports-18.0.1.0.0.2.dist-info/RECORD
