Metadata-Version: 2.1
Name: odoo-addon-l10n_be_mis_reports
Version: 18.0.1.0.0.2
Requires-Python: >=3.10
Requires-Dist: odoo-addon-mis_builder==18.0.*
Requires-Dist: odoo==18.0.*
Summary: MIS Builder templates for the Belgium P&L, Balance Sheets and VAT Declaration
Home-page: https://github.com/OCA/l10n-belgium
License: AGPL-3
Author: ACSONE SA/NV, Odoo Community Association (OCA)
Author-email: support@odoo-community.org
Classifier: Programming Language :: Python
Classifier: Framework :: Odoo
Classifier: Framework :: Odoo :: 18.0
Classifier: License :: OSI Approved :: GNU Affero General Public License v3
